gcdu/__init__.py
gcdu/__main__.py
gcdu/__version__.py
gcdu/cli.py
gcdu/commands/__init__.py
gcdu/commands/export.py
gcdu/commands/import_cmd.py
gcdu/commands/utils.py
gcdu-0.0.5.dist-info/METADATA
gcdu-0.0.5.dist-info/RECORD
gcdu-0.0.5.dist-info/WHEEL
gcdu-0.0.5.dist-info/entry_points.txt
gcdu-0.0.5.dist-info/top_level.txt
